{
  "publicPath": "/_nuxt/",
  "all": [
    "../server/index.spa.html",
    "../server/index.ssr.html",
    "051fbcb.js",
    "0a7f838.js",
    "0ae232e.js",
    "1a08f4e.js",
    "2d06de9.js",
    "65906b1.js",
    "7464ab9.js",
    "75cb911.js",
    "88fb420.js",
    "LICENSES",
    "a220c18.js",
    "a3a8cd5.js",
    "f6f0aff.js",
    "f8a37b0.js",
    "img/css.aec31ad.svg",
    "img/figma-logo.954f334.svg",
    "img/graduation-cap.5c2347f.svg",
    "img/html.50b3a9c.svg",
    "img/instagram.0feb951.svg",
    "img/linkedin.e583fde.svg",
    "img/my-portrait.b3ea4f1.JPG",
    "img/my-portrait.b3ea4f1.jpg",
    "img/nodejs.20b6ca7.svg",
    "img/portfolio-card.e279ae2.jpg",
    "img/react.fdd3331.svg",
    "img/resume.d2fd06d.pdf",
    "img/twitter.a4444ef.svg",
    "img/worker.b46d4b1.svg"
  ],
  "initial": [
    "2d06de9.js",
    "75cb911.js",
    "88fb420.js",
    "a220c18.js"
  ],
  "async": [
    "051fbcb.js",
    "0a7f838.js",
    "0ae232e.js",
    "1a08f4e.js",
    "65906b1.js",
    "7464ab9.js",
    "a3a8cd5.js",
    "f6f0aff.js",
    "f8a37b0.js"
  ],
  "modules": {
    "11921513": [
      9
    ],
    "30538672": [
      12,
      23,
      27,
      26,
      16,
      19,
      24,
      18,
      29,
      25
    ],
    "40540054": [
      9
    ],
    "41568580": [
      9
    ],
    "43822903": [
      12,
      23,
      27,
      26,
      16,
      19,
      24,
      18,
      29,
      25
    ],
    "45777870": [
      3
    ],
    "46120976": [
      15,
      20,
      21,
      28,
      17,
      22
    ],
    "49978500": [
      9
    ],
    "52793740": [
      12,
      23,
      27,
      26,
      16,
      19,
      24,
      18,
      29,
      25
    ],
    "53388303": [
      9
    ],
    "61049982": [
      9
    ],
    "64070560": [
      12,
      23,
      27,
      26,
      16,
      19,
      24,
      18,
      29,
      25
    ],
    "69881341": [
      9
    ],
    "84136426": [
      9
    ],
    "98934148": [
      9
    ],
    "5be6807b": [
      9
    ],
    "8e6189d2": [
      9
    ],
    "7e35ed91": [
      9
    ],
    "083c0624": [
      9
    ],
    "927cde70": [
      9
    ],
    "fe0d1d70": [
      9
    ],
    "7ff61afc": [
      9
    ],
    "676ab210": [
      9
    ],
    "7fc20710": [
      9
    ],
    "464597bf": [
      9
    ],
    "6b2722e4": [
      9
    ],
    "408754c0": [
      9
    ],
    "0e21414e": [
      9
    ],
    "0770d774": [
      9
    ],
    "207612ca": [
      9
    ],
    "8c2a1814": [
      9
    ],
    "088a0686": [
      9
    ],
    "dda868be": [
      9
    ],
    "2183a192": [
      9
    ],
    "cb12aa86": [
      9
    ],
    "4719ff1e": [
      9
    ],
    "56f9b788": [
      9
    ],
    "1d62bffb": [
      9
    ],
    "66c893d6": [
      9
    ],
    "0ae8a9e6": [
      9
    ],
    "5a9fad66": [
      9
    ],
    "51b91d70": [
      10
    ],
    "7e3f2775": [
      9
    ],
    "0af00a3b": [
      9
    ],
    "db89c89c": [
      9
    ],
    "23c284b4": [
      9
    ],
    "0a97b47a": [
      9
    ],
    "0b776eb1": [
      12,
      23,
      27,
      26,
      16,
      19,
      24,
      18,
      29,
      25
    ],
    "c497367c": [
      12,
      23,
      27,
      26,
      16,
      19,
      24,
      18,
      29,
      25
    ],
    "7ec40678": [
      12,
      23,
      27,
      26,
      16,
      19,
      24,
      18,
      29,
      25
    ],
    "3fb70908": [
      12,
      23,
      27,
      26,
      16,
      19,
      24,
      18,
      29,
      25
    ],
    "bb8cdc32": [
      12,
      23,
      27,
      26,
      16,
      19,
      24,
      18,
      29,
      25
    ],
    "510f9622": [
      12,
      23,
      27,
      26,
      16,
      19,
      24,
      18,
      29,
      25
    ],
    "6b1c7042": [
      12,
      23,
      27,
      26,
      16,
      19,
      24,
      18,
      29,
      25
    ],
    "6bccda12": [
      12,
      23,
      27,
      26,
      16,
      19,
      24,
      18,
      29,
      25
    ],
    "2280e23a": [
      12,
      23,
      27,
      26,
      16,
      19,
      24,
      18,
      29,
      25
    ],
    "c8879424": [
      12,
      23,
      27,
      26,
      16,
      19,
      24,
      18,
      29,
      25
    ],
    "96bfb682": [
      12,
      23,
      27,
      26,
      16,
      19,
      24,
      18,
      29,
      25
    ],
    "661acd45": [
      12,
      23,
      27,
      26,
      16,
      19,
      24,
      18,
      29,
      25
    ],
    "611acf80": [
      12,
      23,
      27,
      26,
      16,
      19,
      24,
      18,
      29,
      25
    ],
    "416aeca0": [
      12,
      23,
      27,
      26,
      16,
      19,
      24,
      18,
      29,
      25
    ],
    "5edd4884": [
      12,
      23,
      27,
      26,
      16,
      19,
      24,
      18,
      29,
      25
    ],
    "0873a072": [
      12,
      23,
      27,
      26,
      16,
      19,
      24,
      18,
      29,
      25
    ],
    "52c2e250": [
      12,
      23,
      27,
      26,
      16,
      19,
      24,
      18,
      29,
      25
    ],
    "2452fae6": [
      12,
      23,
      27,
      26,
      16,
      19,
      24,
      18,
      29,
      25
    ],
    "07dd320c": [
      12,
      23,
      27,
      26,
      16,
      19,
      24,
      18,
      29,
      25
    ],
    "5d2f8a9c": [
      12,
      23,
      27,
      26,
      16,
      19,
      24,
      18,
      29,
      25
    ],
    "de169004": [
      12,
      23,
      27,
      26,
      16,
      19,
      24,
      18,
      29,
      25
    ],
    "547855d9": [
      12,
      23,
      27,
      26,
      16,
      19,
      24,
      18,
      29,
      25
    ],
    "72b2d0af": [
      12,
      23,
      27,
      26,
      16,
      19,
      24,
      18,
      29,
      25
    ],
    "29c2d68b": [
      12,
      23,
      27,
      26,
      16,
      19,
      24,
      18,
      29,
      25
    ],
    "fccfc660": [
      9
    ],
    "05308522": [
      9
    ],
    "7dd323ac": [
      9
    ],
    "b19faf1e": [
      9
    ],
    "3fafc7e8": [
      9
    ],
    "4f7f58ea": [
      9
    ],
    "1b144a2c": [
      9
    ],
    "6d12f919": [
      9
    ],
    "828105f6": [
      9
    ],
    "1f0890df": [
      9
    ],
    "65392e39": [
      9
    ],
    "1570c713": [
      9
    ],
    "52b7e3b2": [
      9
    ],
    "7995b142": [
      9
    ],
    "2aea7956": [
      9
    ],
    "95d0e09e": [
      9
    ],
    "922eeee0": [
      9
    ],
    "19a149dd": [
      10
    ],
    "4e7e6531": [
      10
    ],
    "4c341694": [
      10
    ],
    "0d91c4ce": [
      9
    ],
    "db67d516": [
      9
    ],
    "64fff12e": [
      9
    ],
    "732baa72": [
      9
    ],
    "415d18c6": [
      9
    ],
    "2210ab3a": [
      9
    ],
    "3603e2aa": [
      9
    ],
    "46f045dd": [
      9
    ],
    "45b0f1af": [
      9
    ],
    "1a373ace": [
      9
    ],
    "79a31455": [
      9
    ],
    "17a9c9de": [
      9
    ],
    "550a5952": [
      9
    ],
    "69b19e34": [
      9
    ],
    "18f2ffe6": [
      10
    ],
    "4e47da75": [
      9
    ],
    "597c82d6": [
      9
    ],
    "443e5374": [
      9
    ],
    "684de158": [
      9
    ],
    "0def103e": [
      9
    ],
    "05bd4221": [
      9
    ],
    "1a71ec84": [
      9
    ],
    "52c9711c": [
      9
    ],
    "1406da90": [
      9
    ],
    "03a0e63a": [
      9
    ],
    "20f9f594": [
      9
    ],
    "8e195358": [
      9
    ],
    "42b68a0d": [
      9
    ],
    "5c9ba2b0": [
      9
    ],
    "0b1bd407": [
      9
    ],
    "2bf2da58": [
      9
    ],
    "5286ec63": [
      9
    ],
    "183449d9": [
      9
    ],
    "b2bbec3c": [
      9
    ],
    "5e6b59d0": [
      9
    ],
    "66c1240a": [
      9
    ],
    "e6e38faa": [
      9
    ],
    "c6956034": [
      9
    ],
    "a54bb27a": [
      9
    ],
    "743854f4": [
      9
    ],
    "0a2ba18c": [
      9
    ],
    "40000a56": [
      9
    ],
    "85916ad8": [
      9
    ],
    "2b469c14": [
      9
    ],
    "01a91976": [
      9
    ],
    "5def55da": [
      9
    ],
    "4e65abcc": [
      9
    ],
    "57e73cd1": [
      9
    ],
    "0ab63ba4": [
      9
    ],
    "9dc0fe4a": [
      9
    ],
    "211e99f6": [
      9
    ],
    "3a6b141e": [
      9
    ],
    "408f40da": [
      9
    ],
    "e4c5c3f0": [
      9
    ],
    "6ee9a3c2": [
      9
    ],
    "138aab05": [
      9
    ],
    "d86ebc64": [
      9
    ],
    "cbf7c296": [
      12,
      23,
      27,
      26,
      16,
      19,
      24,
      18,
      29,
      25
    ],
    "11664f10": [
      12,
      23,
      27,
      26,
      16,
      19,
      24,
      18,
      29,
      25
    ],
    "b993ad96": [
      12,
      23,
      27,
      26,
      16,
      19,
      24,
      18,
      29,
      25
    ],
    "2210fb44": [
      12,
      23,
      27,
      26,
      16,
      19,
      24,
      18,
      29,
      25
    ],
    "2bc35508": [
      12,
      23,
      27,
      26,
      16,
      19,
      24,
      18,
      29,
      25
    ],
    "f3c187de": [
      12,
      23,
      27,
      26,
      16,
      19,
      24,
      18,
      29,
      25
    ],
    "45103dc7": [
      9
    ],
    "daaf579c": [
      9
    ],
    "59aa0f7e": [
      9
    ],
    "370c5a5a": [
      9
    ],
    "54eb3e52": [
      9
    ],
    "95c9aaec": [
      9
    ],
    "e714611e": [
      9
    ],
    "122c5526": [
      9
    ],
    "4fe7886a": [
      9
    ],
    "6afe47ec": [
      9
    ],
    "bf1f6a62": [
      9
    ],
    "0bd172f0": [
      9
    ],
    "7108c8cc": [
      9
    ],
    "f97926e2": [
      9
    ],
    "6491d7bc": [
      9
    ],
    "57a7203c": [
      9
    ],
    "2fdfecd2": [
      9
    ],
    "7147c22e": [
      9
    ],
    "8468482e": [
      9
    ],
    "2f1287c4": [
      9
    ],
    "c42a5dac": [
      9
    ],
    "394c7cd8": [
      9
    ],
    "75fb1cb5": [
      9
    ],
    "60335e54": [
      12,
      23,
      27,
      26,
      16,
      19,
      24,
      18,
      29,
      25
    ],
    "864a4898": [
      12,
      23,
      27,
      26,
      16,
      19,
      24,
      18,
      29,
      25
    ],
    "e49ac54c": [
      12,
      23,
      27,
      26,
      16,
      19,
      24,
      18,
      29,
      25
    ],
    "31764d41": [
      12,
      23,
      27,
      26,
      16,
      19,
      24,
      18,
      29,
      25
    ],
    "aff050a6": [
      12,
      23,
      27,
      26,
      16,
      19,
      24,
      18,
      29,
      25
    ],
    "a4214362": [
      12,
      23,
      27,
      26,
      16,
      19,
      24,
      18,
      29,
      25
    ],
    "6974a09c": [
      12,
      23,
      27,
      26,
      16,
      19,
      24,
      18,
      29,
      25
    ],
    "0228504e": [
      12,
      23,
      27,
      26,
      16,
      19,
      24,
      18,
      29,
      25
    ],
    "0493441f": [
      10
    ],
    "027c2891": [
      9
    ],
    "15f37088": [
      12,
      23,
      27,
      26,
      16,
      19,
      24,
      18,
      29,
      25
    ],
    "32bcd15f": [
      9
    ],
    "ed605918": [
      9
    ],
    "0d5558cb": [
      9
    ],
    "56d37625": [
      9
    ],
    "263ba090": [
      9
    ],
    "b7c7923a": [
      9
    ],
    "5092952c": [
      9
    ],
    "672b9cd2": [
      9
    ],
    "01d22262": [
      9
    ],
    "14ea1433": [
      9
    ],
    "9243ad18": [
      9
    ],
    "0e6ef4c0": [
      9
    ],
    "07a5d66c": [
      9
    ],
    "413049e4": [
      9
    ],
    "b90286ce": [
      9
    ],
    "1715c002": [
      9
    ],
    "4ed298e9": [
      9
    ],
    "df40f08a": [
      9
    ],
    "2c3c5344": [
      9
    ],
    "561ab17c": [
      9
    ],
    "a2b77a50": [
      9
    ],
    "1ef5b0b2": [
      9
    ],
    "0f76b6ce": [
      9
    ],
    "6921c0a6": [
      9
    ],
    "65ae8f2e": [
      9
    ],
    "3669ecd1": [
      9
    ],
    "27709f2e": [
      9
    ],
    "117a2770": [
      9
    ],
    "6c77fcae": [
      9
    ],
    "2642eeed": [
      9
    ],
    "78220c59": [
      9
    ],
    "7b790a12": [
      9
    ],
    "65d74482": [
      9
    ],
    "409140a8": [
      9
    ],
    "9d06d62c": [
      9
    ],
    "ebf2fad6": [
      9
    ],
    "3df21526": [
      9
    ],
    "353baf6b": [
      9
    ],
    "70d61fe6": [
      9
    ],
    "c946eb92": [
      9
    ],
    "1817093f": [
      9
    ],
    "78d6912a": [
      9
    ],
    "455f4248": [
      12,
      23,
      27,
      26,
      16,
      19,
      24,
      18,
      29,
      25
    ],
    "ed4b66d2": [
      12,
      23,
      27,
      26,
      16,
      19,
      24,
      18,
      29,
      25
    ],
    "59093f4a": [
      10
    ],
    "662af010": [
      12,
      23,
      27,
      26,
      16,
      19,
      24,
      18,
      29,
      25
    ],
    "8a1605a0": [
      12,
      23,
      27,
      26,
      16,
      19,
      24,
      18,
      29,
      25
    ],
    "638fbbc4": [
      12,
      23,
      27,
      26,
      16,
      19,
      24,
      18,
      29,
      25
    ],
    "70c406de": [
      12,
      23,
      27,
      26,
      16,
      19,
      24,
      18,
      29,
      25
    ],
    "2d588984": [
      10
    ],
    "04952a1f": [
      9
    ],
    "f3536c94": [
      10
    ],
    "f77588a2": [
      10
    ],
    "66527b95": [
      10
    ],
    "4c5a7c56": [
      12,
      23,
      27,
      26,
      16,
      19,
      24,
      18,
      29,
      25
    ],
    "5184f808": [
      10
    ],
    "1ace0088": [
      10
    ],
    "5f7dd5e7": [
      12,
      23,
      27,
      26,
      16,
      19,
      24,
      18,
      29,
      25
    ],
    "e1cf798a": [
      12,
      23,
      27,
      26,
      16,
      19,
      24,
      18,
      29,
      25
    ],
    "f5a426f0": [
      12,
      23,
      27,
      26,
      16,
      19,
      24,
      18,
      29,
      25
    ],
    "204aee75": [
      12,
      23,
      27,
      26,
      16,
      19,
      24,
      18,
      29,
      25
    ],
    "14198af4": [
      12,
      23,
      27,
      26,
      16,
      19,
      24,
      18,
      29,
      25
    ],
    "d07219f0": [
      12,
      23,
      27,
      26,
      16,
      19,
      24,
      18,
      29,
      25
    ],
    "446b9b01": [
      12,
      23,
      27,
      26,
      16,
      19,
      24,
      18,
      29,
      25
    ],
    "8ca1b3dc": [
      12,
      23,
      27,
      26,
      16,
      19,
      24,
      18,
      29,
      25
    ],
    "1d974e38": [
      12,
      23,
      27,
      26,
      16,
      19,
      24,
      18,
      29,
      25
    ],
    "454bccac": [
      12,
      23,
      27,
      26,
      16,
      19,
      24,
      18,
      29,
      25
    ],
    "61b81a77": [
      12,
      23,
      27,
      26,
      16,
      19,
      24,
      18,
      29,
      25
    ],
    "6a15ccb7": [
      12,
      23,
      27,
      26,
      16,
      19,
      24,
      18,
      29,
      25
    ],
    "b3b5f5a0": [
      12,
      23,
      27,
      26,
      16,
      19,
      24,
      18,
      29,
      25
    ],
    "119e7bcb": [
      12,
      23,
      27,
      26,
      16,
      19,
      24,
      18,
      29,
      25
    ],
    "d6d9a604": [
      12,
      23,
      27,
      26,
      16,
      19,
      24,
      18,
      29,
      25
    ],
    "bcba8850": [
      12,
      23,
      27,
      26,
      16,
      19,
      24,
      18,
      29,
      25
    ],
    "1d3e6451": [
      12,
      23,
      27,
      26,
      16,
      19,
      24,
      18,
      29,
      25
    ],
    "4efc394e": [
      12,
      23,
      27,
      26,
      16,
      19,
      24,
      18,
      29,
      25
    ],
    "385473f6": [
      12,
      23,
      27,
      26,
      16,
      19,
      24,
      18,
      29,
      25
    ],
    "38a53b75": [
      12,
      23,
      27,
      26,
      16,
      19,
      24,
      18,
      29,
      25
    ],
    "6cee1492": [
      12,
      23,
      27,
      26,
      16,
      19,
      24,
      18,
      29,
      25
    ],
    "565f1448": [
      12,
      23,
      27,
      26,
      16,
      19,
      24,
      18,
      29,
      25
    ],
    "7d311d52": [
      12,
      23,
      27,
      26,
      16,
      19,
      24,
      18,
      29,
      25
    ],
    "26a6d53e": [
      12,
      23,
      27,
      26,
      16,
      19,
      24,
      18,
      29,
      25
    ],
    "7ecef1b7": [
      12,
      23,
      27,
      26,
      16,
      19,
      24,
      18,
      29,
      25
    ],
    "15e4b84b": [
      12,
      23,
      27,
      26,
      16,
      19,
      24,
      18,
      29,
      25
    ],
    "1af9b3ec": [
      12,
      23,
      27,
      26,
      16,
      19,
      24,
      18,
      29,
      25
    ],
    "36298fd4": [
      9
    ],
    "fdd9c0f4": [
      9
    ],
    "3fb8ddfa": [
      12,
      23,
      27,
      26,
      16,
      19,
      24,
      18,
      29,
      25
    ],
    "1a560538": [
      12,
      23,
      27,
      26,
      16,
      19,
      24,
      18,
      29,
      25
    ],
    "0b6eddaa": [
      12,
      23,
      27,
      26,
      16,
      19,
      24,
      18,
      29,
      25
    ],
    "163265a2": [
      12,
      23,
      27,
      26,
      16,
      19,
      24,
      18,
      29,
      25
    ],
    "4567a9aa": [
      12,
      23,
      27,
      26,
      16,
      19,
      24,
      18,
      29,
      25
    ],
    "4746c86a": [
      12,
      23,
      27,
      26,
      16,
      19,
      24,
      18,
      29,
      25
    ],
    "36bcc99c": [
      12,
      23,
      27,
      26,
      16,
      19,
      24,
      18,
      29,
      25
    ],
    "1bfc0c49": [
      12,
      23,
      27,
      26,
      16,
      19,
      24,
      18,
      29,
      25
    ],
    "517c3bf3": [
      12,
      23,
      27,
      26,
      16,
      19,
      24,
      18,
      29,
      25
    ],
    "56111afe": [
      12,
      23,
      27,
      26,
      16,
      19,
      24,
      18,
      29,
      25
    ],
    "3783fd9b": [
      12,
      23,
      27,
      26,
      16,
      19,
      24,
      18,
      29,
      25
    ],
    "ca7e059a": [
      12,
      23,
      27,
      26,
      16,
      19,
      24,
      18,
      29,
      25
    ],
    "1eaa2c82": [
      10
    ],
    "222aa100": [
      12,
      23,
      27,
      26,
      16,
      19,
      24,
      18,
      29,
      25
    ],
    "1f5b7d70": [
      9
    ],
    "5cd6fa2a": [
      9
    ],
    "e7d96d78": [
      9
    ],
    "108747ae": [
      9
    ],
    "68058d6e": [
      9
    ],
    "12d807ef": [
      9
    ],
    "d4d4e3f4": [
      9
    ],
    "17956e4e": [
      9
    ],
    "1f2a748e": [
      9
    ],
    "3d11a5ed": [
      9
    ],
    "4e1ce42d": [
      9
    ],
    "082e8be8": [
      9
    ],
    "566d2892": [
      9
    ],
    "7b39e259": [
      9
    ],
    "6332f9b5": [
      9
    ],
    "44abded5": [
      9
    ],
    "74c6253a": [
      9
    ],
    "9cd10136": [
      9
    ],
    "daf7c708": [
      9
    ],
    "233c2e2c": [
      9
    ],
    "e39ec11c": [
      9
    ],
    "540f9033": [
      9
    ],
    "654e1aae": [
      9
    ],
    "36c08d58": [
      9
    ],
    "96d9b2e4": [
      9
    ],
    "1dbafe00": [
      9
    ],
    "0ab322fa": [
      9
    ],
    "2038773e": [
      9
    ],
    "23c799c6": [
      9
    ],
    "287428e8": [
      9
    ],
    "74dd6f96": [
      9
    ],
    "5222f732": [
      9
    ],
    "893bea5c": [
      9
    ],
    "36cf7594": [
      9
    ],
    "19a8a591": [
      9
    ],
    "11e877ae": [
      9
    ],
    "e6a2b492": [
      9
    ],
    "718893c1": [
      9
    ],
    "1abf79dd": [
      9
    ],
    "0a770a76": [
      9
    ],
    "0a4fd964": [
      9
    ],
    "0ddefbec": [
      9
    ],
    "61471ba7": [
      9
    ],
    "493de8ba": [
      9
    ],
    "0af94bac": [
      9
    ],
    "0002b8c2": [
      9
    ],
    "406ded13": [
      9
    ],
    "31833d0f": [
      9
    ],
    "9705aec4": [
      9
    ],
    "68b63b79": [
      9
    ],
    "6ca0c9b4": [
      9
    ],
    "0a79f381": [
      9
    ],
    "442e3586": [
      9
    ],
    "3983fd39": [
      9
    ],
    "6b0191a4": [
      12,
      23,
      27,
      26,
      16,
      19,
      24,
      18,
      29,
      25
    ],
    "18c12c2b": [
      12,
      23,
      27,
      26,
      16,
      19,
      24,
      18,
      29,
      25
    ],
    "33974f2e": [
      12,
      23,
      27,
      26,
      16,
      19,
      24,
      18,
      29,
      25
    ],
    "a865fbb4": [
      12,
      23,
      27,
      26,
      16,
      19,
      24,
      18,
      29,
      25
    ],
    "8c8548e0": [
      12,
      23,
      27,
      26,
      16,
      19,
      24,
      18,
      29,
      25
    ],
    "24200cde": [
      10
    ],
    "4c91d790": [
      10
    ],
    "09ab3dc2": [
      10
    ],
    "a411c928": [
      10
    ],
    "f10587fe": [
      12,
      23,
      27,
      26,
      16,
      19,
      24,
      18,
      29,
      25
    ],
    "6fda3aae": [
      10
    ],
    "f85dc224": [
      10
    ],
    "dd87657e": [
      10
    ],
    "4eba5460": [
      10
    ],
    "270ed2d0": [
      15,
      20,
      21,
      28,
      17,
      22
    ],
    "f2a6bb06": [
      15,
      20,
      21,
      28,
      17,
      22
    ],
    "29a41944": [
      15,
      20,
      21,
      28,
      17,
      22
    ],
    "16b0e28a": [
      15,
      20,
      21,
      28,
      17,
      22
    ],
    "73d92ab1": [
      15,
      20,
      21,
      28,
      17,
      22
    ],
    "ca6d3526": [
      15,
      20,
      21,
      28,
      17,
      22
    ],
    "4479ac5e": [
      15,
      20,
      21,
      28,
      17,
      22
    ],
    "3762b0e4": [
      15,
      20,
      21,
      28,
      17,
      22
    ],
    "cb7adaa4": [
      15,
      20,
      21,
      28,
      17,
      22
    ],
    "7493edfb": [
      15,
      20,
      21,
      28,
      17,
      22
    ],
    "33f14096": [
      15,
      20,
      21,
      28,
      17,
      22
    ],
    "ba87e6f0": [
      15,
      20,
      21,
      28,
      17,
      22
    ],
    "3aef70b8": [
      15,
      20,
      21,
      28,
      17,
      22
    ],
    "32f13471": [
      15,
      20,
      21,
      28,
      17,
      22
    ],
    "0931949c": [
      15,
      20,
      21,
      28,
      17,
      22
    ],
    "14911f40": [
      15,
      20,
      21,
      28,
      17,
      22
    ],
    "15f468c8": [
      15,
      20,
      21,
      28,
      17,
      22
    ],
    "dda18d6c": [
      13,
      15
    ],
    "d2d61372": [
      13,
      15
    ],
    "1fb4e372": [
      13,
      15
    ],
    "46fc3dda": [
      13,
      15
    ],
    "0a4a507f": [
      13,
      15
    ],
    "38c6bb5e": [
      3
    ],
    "7ed8533e": [
      3
    ],
    "7fef72eb": [
      3
    ],
    "134cb9de": [
      3
    ],
    "80f3b120": [
      7
    ],
    "d59e8170": [
      7
    ],
    "042254e8": [
      7
    ],
    "314d934a": [
      7
    ],
    "69fea319": [
      7
    ],
    "f8321fd2": [
      14
    ],
    "c56a1544": [
      14
    ],
    "01f97c77": [
      14
    ],
    "5d04602a": [
      14
    ],
    "89b96d6c": [
      14
    ],
    "3e672dac": [
      5
    ],
    "8d39c73a": [
      5
    ],
    "a64ab560": [
      5
    ],
    "25cf57f6": [
      5
    ],
    "42709e5d": [
      5
    ]
  },
  "assetsMapping": {
    "21701e74": [
      "051fbcb.js"
    ],
    "f80ac508": [
      "0a7f838.js"
    ],
    "3d7e8ac8": [
      "0ae232e.js"
    ],
    "4cf83bf0": [
      "1a08f4e.js"
    ],
    "6fca0322": [
      "2d06de9.js"
    ],
    "61aeb699": [
      "65906b1.js"
    ],
    "203e3b0b": [
      "7464ab9.js"
    ],
    "085a35c4": [
      "75cb911.js"
    ],
    "7ea24c87": [
      "88fb420.js"
    ],
    "1a3ae26b": [
      "a220c18.js"
    ],
    "2a130dde": [
      "a3a8cd5.js"
    ],
    "f642dcfa": [
      "f6f0aff.js"
    ],
    "d4d1324a": [
      "f8a37b0.js"
    ]
  }
}